README.rst
httpie_unixsocket.py
setup.py
httpie_unixsocket.egg-info/PKG-INFO
httpie_unixsocket.egg-info/SOURCES.txt
httpie_unixsocket.egg-info/dependency_links.txt
httpie_unixsocket.egg-info/entry_points.txt
httpie_unixsocket.egg-info/not-zip-safe
httpie_unixsocket.egg-info/pbr.json
httpie_unixsocket.egg-info/requires.txt
httpie_unixsocket.egg-info/top_level.txt