Metadata-Version: 1.1
Name: httpie-unixsocket
Version: 0.0.0
Summary: UNIX socket auth plugin for HTTPie.
Home-page: https://github.com/msabramo/httpie-unixsocket
Author: Jakub Roztocil
Author-email: jakub@roztocil.name
License: BSD
Download-URL: https://github.com/msabramo/httpie-unixsocket
Platform: UNKNOWN
Classifier: Development Status :: 5 - Production/Stable
Classifier: Programming Language :: Python
Classifier: Programming Language :: Python :: 2
Classifier: Programming Language :: Python :: 2.6
Classifier: Programming Language :: Python :: 2.7
Classifier: Programming Language :: Python :: 3
Classifier: Programming Language :: Python :: 3.3
Classifier: Programming Language :: Python :: 3.4
Classifier: Environment :: Plugins
Classifier: License :: OSI Approved :: BSD License
Classifier: Topic :: Internet :: WWW/HTTP
Classifier: Topic :: Utilities
